{"name":"Liechtenstein","iso2":"LI","phone_code":"423","states":[{"name":"Balzers","state_code":"01","cities":["Balzers"]},{"name":"Eschen","state_code":"02","cities":["Eschen"]},{"name":"Gamprin","state_code":"03","cities":["Gamprin"]},{"name":"Mauren","state_code":"04","cities":["Mauren"]},{"name":"Planken","state_code":"05","cities":["Planken"]},{"name":"Ruggell","state_code":"06","cities":["Ruggell"]},{"name":"Schaan","state_code":"07","cities":["Schaan"]},{"name":"Schellenberg","state_code":"08","cities":["Schellenberg"]},{"name":"Triesen","state_code":"09","cities":["Triesen"]},{"name":"Triesenberg","state_code":"10","cities":["Triesenberg"]},{"name":"Vaduz","state_code":"11","cities":["Vaduz"]}]}